langchain_amorce/__init__.py
langchain_amorce/a2a.py
langchain_amorce/agent.py
langchain_amorce/tools.py
langchain_amorce-0.1.0.dist-info/METADATA
langchain_amorce-0.1.0.dist-info/WHEEL
langchain_amorce-0.1.0.dist-info/top_level.txt
langchain_amorce-0.1.0.dist-info/RECORD
