Metadata-Version: 2.4
Name: langchain-amorce
Version: 0.1.0
Summary: Secure LangChain agents with Amorce (Ed25519 + HITL + A2A)
Home-page: https://github.com/amorce/langchain-amorce
Author: Amorce Team
Author-email: team@amorce.io
Project-URL: Bug Tracker, https://github.com/amorce/langchain-amorce/issues
Project-URL: Documentation, https://amorce.io/docs
Project-URL: Source Code, https://github.com/amorce/langchain-amorce
Keywords: langchain amorce ai agents security ed25519 signatures hitl a2a
Classifier: Development Status :: 4 - Beta
Classifier: Intended Audience :: Developers
Classifier: License :: OSI Approved :: MIT License
Classifier: Programming Language :: Python :: 3.9
Classifier: Programming Language :: Python :: 3.10
Classifier: Programming Language :: Python :: 3.11
Classifier: Programming Language :: Python :: 3.12
Classifier: Topic :: Software Development :: Libraries :: Python Modules
Classifier: Topic :: Scientific/Engineering :: Artificial Intelligence
Requires-Python: >=3.9
Requires-Dist: amorce-sdk>=0.2.1
Requires-Dist: langchain>=0.1.0
Requires-Dist: langchain-community>=0.0.1
Requires-Dist: langchain-core>=0.1.0
Dynamic: author
Dynamic: author-email
Dynamic: classifier
Dynamic: description
Dynamic: description-content-type
Dynamic: home-page
Dynamic: keywords
Dynamic: project-url
Dynamic: requires-dist
Dynamic: requires-python
Dynamic: summary
